imx500_converter/__init__.py
imx500_converter/__version.py
imx500_converter/main_pt.py
imx500_converter/main_tf.py
imx500_converter/converter/__init__.py
imx500_converter/converter/converter.py
imx500_converter/converter/imx_cfg.py
imx500_converter/converter/imx_cfg_file_reader.py
imx500_converter/converter/sdspconv_runner.py
imx500_converter/converter/uni_converter_runner.py
imx500_converter/converter/util/__init__.py
imx500_converter/converter/util/cli.py
imx500_converter/converter/util/error.py
imx500_converter/converter/util/keys_case.py
imx500_converter/converter/util/logger.py
imx500_converter-3.17.3.dist-info/METADATA
imx500_converter-3.17.3.dist-info/WHEEL
imx500_converter-3.17.3.dist-info/entry_points.txt
imx500_converter-3.17.3.dist-info/top_level.txt
imx500_converter-3.17.3.dist-info/RECORD
