Metadata-Version: 2.4
Name: imx500-converter
Version: 3.17.3
Author: ssi-dnn-dev
Author-email: ssi-dnn-dev@sony.com
Maintainer: ssi-dnn-dev
Maintainer-email: ssi-dnn-dev@sony.com
Requires-Dist: sdspconv~=3.17.1
Provides-Extra: tf
Requires-Dist: uni-tensorflow==3.17.1; extra == "tf"
Provides-Extra: pt
Requires-Dist: uni-pytorch==3.17.1; extra == "pt"
Dynamic: author
Dynamic: author-email
Dynamic: maintainer
Dynamic: maintainer-email
Dynamic: provides-extra
Dynamic: requires-dist
